Metadata-Version: 1.0
Name: data-constructor
Version: 0.0
Summary: data_constructor
Home-page: UNKNOWN
Author: UNKNOWN
Author-email: max.taran.210@mail.ru
License: UNKNOWN
Platform: UNKNOWN
